danrerlib/GO.py
danrerlib/KEGG.py
danrerlib/__init__.py
danrerlib/database/GO/GO_dreM_V1.txt
danrerlib/database/GO/GO_dre_V1.txt
danrerlib/database/GO/GO_hsa_V1.txt
danrerlib/database/GO/GO_ids_V1.txt
danrerlib/database/KEGG/disease_ids_V1.txt
danrerlib/database/KEGG/disease_ids_and_genes_V1.txt
danrerlib/database/KEGG/disease_ids_dreM_and_genes_V1.txt
danrerlib/database/KEGG/disease_ids_valid_V1.txt
danrerlib/database/KEGG/dre/dre00010.txt
danrerlib/database/KEGG/dre/dre00020.txt
danrerlib/database/KEGG/dre/dre00030.txt
danrerlib/database/KEGG/dre/dre00040.txt
danrerlib/database/KEGG/dre/dre00051.txt
danrerlib/database/KEGG/dre/dre00052.txt
danrerlib/database/KEGG/dre/dre00053.txt
danrerlib/database/KEGG/dre/dre00061.txt
danrerlib/database/KEGG/dre/dre00062.txt
danrerlib/database/KEGG/dre/dre00071.txt
danrerlib/database/KEGG/dre/dre00100.txt
danrerlib/database/KEGG/dre/dre00120.txt
danrerlib/database/KEGG/dre/dre00130.txt
danrerlib/database/KEGG/dre/dre00140.txt
danrerlib/database/KEGG/dre/dre00190.txt
danrerlib/database/KEGG/dre/dre00220.txt
danrerlib/database/KEGG/dre/dre00230.txt
danrerlib/database/KEGG/dre/dre00232.txt
danrerlib/database/KEGG/dre/dre00240.txt
danrerlib/database/KEGG/dre/dre00250.txt
danrerlib/database/KEGG/dre/dre00260.txt
danrerlib/database/KEGG/dre/dre00270.txt
danrerlib/database/KEGG/dre/dre00280.txt
danrerlib/database/KEGG/dre/dre00290.txt
danrerlib/database/KEGG/dre/dre00310.txt
danrerlib/database/KEGG/dre/dre00330.txt
danrerlib/database/KEGG/dre/dre00340.txt
danrerlib/database/KEGG/dre/dre00350.txt
danrerlib/database/KEGG/dre/dre00360.txt
danrerlib/database/KEGG/dre/dre00380.txt
danrerlib/database/KEGG/dre/dre00400.txt
danrerlib/database/KEGG/dre/dre00410.txt
danrerlib/database/KEGG/dre/dre00430.txt
danrerlib/database/KEGG/dre/dre00440.txt
danrerlib/database/KEGG/dre/dre00450.txt
danrerlib/database/KEGG/dre/dre00470.txt
danrerlib/database/KEGG/dre/dre00480.txt
danrerlib/database/KEGG/dre/dre00500.txt
danrerlib-0.1.5.dist-info/LICENSE
danrerlib-0.1.5.dist-info/METADATA
danrerlib-0.1.5.dist-info/WHEEL
danrerlib-0.1.5.dist-info/RECORD
